seq_detector.sv
module seq_detector(
   input seq_in, clk, reset,
   output logic detect_out
);

   //one-hot encoding of FSM
   enum logic [4:0] {S0 = 5'b00001, S1 = 5'b00010, S2 = 5'b00100, S3 = 5'b01000, S4 = 5'b10000}  state, next;

   //state registers
   always_ff @(posedge clk or posedge reset)
     if (reset) state <= S0;
     else       state <= next;

   // Next state assignment logic
   always_comb begin
     next = state;
     unique case (state)
       S0 : if (seq_in) next = S1; else next = S0;
       S1 : if (seq_in) next = S1; else next = S2;
       S2 : if (seq_in) next = S3; else next = S0;
       S3 : if (seq_in) next = S4; else next = S2;
       S4 : next = S0;
     endcase
     $monitor(state);
   end

   // Registered output logic
   always_ff @(posedge clk, posedge reset)
     if (reset) detect_out <= 1'b0;
     else       detect_out <= (state == S4);

ASSUME_VALID_STATE1: assume property ($onehot(state));
ASSUME_VALID_STATE2: assume property (reset |-> (state == S0));

ASSERT_NON_OVERLAPPING_PROPERTY: assert property (@(posedge clk) (state == S4) |-> (next == S0));
ASSERT_CHK_SEQ_DETECT: assert property (@(posedge clk) disable iff (reset) seq_in ##1 !seq_in ##1 seq_in ##1 seq_in  |-> ##2 (detect_out || $past(detect_out, 5) == 0));
ASSERT_NO_CONTINUOUS_DETECT_OUT: assert property (@(posedge clk) disable iff (reset) detect_out |-> (($past(detect_out) != 1) && ($past(detect_out,2) != 1) && ($past(detect_out,3) != 1) && ($past(detect_out,4) != 1)));
ASSERT_BI: assert property ( @(posedge clk)  disable iff (reset) detect_out |-> (($past(seq_in, 2) == 1) && ($past(seq_in, 3) == 1) && ($past(seq_in, 4) == 0) && ($past(seq_in, 5) == 1)) );

COVER_NON_OVERLAPPING_SEQUENCE: cover property (seq_in ##1 !seq_in ##1 seq_in ##1 seq_in ##2 !seq_in);
COVER_OVERLAPPING_SEQUENCE: cover property (seq_in ##1 !seq_in ##1 seq_in ##1 seq_in ##1 seq_in ##1 !seq_in ##1 seq_in ##3 seq_in);

endmodule

ebmc_counter.vcd
$date
  Tue Aug  6 19:38:46 2024
$end
$timescale
  1ns
$end
$scope module seq_detector $end
  $var wire 5 seq_detector.S0 S0 [4:0] $end
  $var wire 5 seq_detector.S1 S1 [4:0] $end
  $var wire 5 seq_detector.S2 S2 [4:0] $end
  $var wire 5 seq_detector.S3 S3 [4:0] $end
  $var wire 5 seq_detector.S4 S4 [4:0] $end
  $var wire 1 seq_detector.seq_in seq_in $end
  $var wire 1 seq_detector.clk clk $end
  $var wire 1 seq_detector.reset reset $end
  $var reg 1 seq_detector.detect_out detect_out $end
  $var reg 5 seq_detector.state state [4:0] $end
  $var wire 5 seq_detector.next next [4:0] $end
$upscope $end
$enddefinitions $end
#0
1seq_detector.seq_in
1seq_detector.reset
0seq_detector.detect_out
b00001 seq_detector.S0
b00010 seq_detector.S1
b00100 seq_detector.S2
b01000 seq_detector.S3
b10000 seq_detector.S4
b00001 seq_detector.state
b00010 seq_detector.next
#1
0seq_detector.reset
#2
0seq_detector.seq_in
b00010 seq_detector.state
b00100 seq_detector.next
#3
1seq_detector.seq_in
b00100 seq_detector.state
b01000 seq_detector.next
#4
0seq_detector.seq_in
b01000 seq_detector.state
b00100 seq_detector.next
#5
1seq_detector.seq_in
b00100 seq_detector.state
b01000 seq_detector.next
#6
0seq_detector.seq_in
b01000 seq_detector.state
b00100 seq_detector.next
#7
1seq_detector.seq_in
b00100 seq_detector.state
b01000 seq_detector.next
#8
0seq_detector.seq_in
b01000 seq_detector.state
b00100 seq_detector.next
#9
1seq_detector.seq_in
b00100 seq_detector.state
b01000 seq_detector.next
#10
0seq_detector.seq_in
b01000 seq_detector.state
b00100 seq_detector.next
#11
1seq_detector.seq_in
b00100 seq_detector.state
b01000 seq_detector.next
#12
b01000 seq_detector.state
b10000 seq_detector.next
#13
0seq_detector.seq_in
b10000 seq_detector.state
b00001 seq_detector.next
#14
1seq_detector.seq_in
1seq_detector.detect_out
b00001 seq_detector.state
b00010 seq_detector.next
#15
0seq_detector.seq_in
0seq_detector.detect_out
b00010 seq_detector.state
b00100 seq_detector.next
#16
b00100 seq_detector.state
b00001 seq_detector.next
#17
1seq_detector.seq_in
b00001 seq_detector.state
b00010 seq_detector.next
#18
b00010 seq_detector.state
#19
#20
#21
#22
0seq_detector.seq_in
b00100 seq_detector.next
#23
1seq_detector.seq_in
b00100 seq_detector.state
b01000 seq_detector.next
#24
0seq_detector.seq_in
b01000 seq_detector.state
b00100 seq_detector.next
#25
1seq_detector.seq_in
b00100 seq_detector.state
b01000 seq_detector.next
#26
0seq_detector.seq_in
b01000 seq_detector.state
b00100 seq_detector.next
#27
b00100 seq_detector.state
b00001 seq_detector.next
#28
1seq_detector.seq_in
b00001 seq_detector.state
b00010 seq_detector.next
#29
b00010 seq_detector.state
#30
0seq_detector.seq_in
b00100 seq_detector.next
#31
1seq_detector.seq_in
b00100 seq_detector.state
b01000 seq_detector.next
#32
0seq_detector.seq_in
b01000 seq_detector.state
b00100 seq_detector.next
#33
1seq_detector.seq_in
b00100 seq_detector.state
b01000 seq_detector.next
#34
b01000 seq_detector.state
b10000 seq_detector.next
#35
b10000 seq_detector.state
b00001 seq_detector.next
#36
1seq_detector.detect_out
b00001 seq_detector.state
b00010 seq_detector.next
#37
0seq_detector.seq_in
0seq_detector.detect_out
b00010 seq_detector.state
b00100 seq_detector.next
#38
1seq_detector.seq_in
b00100 seq_detector.state
b01000 seq_detector.next
#39
b01000 seq_detector.state
b10000 seq_detector.next
#40
0seq_detector.seq_in
b10000 seq_detector.state
b00001 seq_detector.next
#41
1seq_detector.seq_in
1seq_detector.detect_out
b00001 seq_detector.state
b00010 seq_detector.next
#42
0seq_detector.seq_in
0seq_detector.detect_out
b00010 seq_detector.state
b00100 seq_detector.next
#43
1seq_detector.seq_in
b00100 seq_detector.state
b01000 seq_detector.next
#44
b01000 seq_detector.state
b10000 seq_detector.next
#45
b10000 seq_detector.state
b00001 seq_detector.next
#46
1seq_detector.detect_out
b00001 seq_detector.state
b00010 seq_detector.next
#47
0seq_detector.detect_out
b00010 seq_detector.state
#48
0seq_detector.seq_in
b00100 seq_detector.next
#49
1seq_detector.seq_in
b00100 seq_detector.state
b01000 seq_detector.next
#50
0seq_detector.seq_in
b01000 seq_detector.state
b00100 seq_detector.next
#51
b00100 seq_detector.state
b00001 seq_detector.next
#52
b00001 seq_detector.state
#53
1seq_detector.seq_in
b00010 seq_detector.next
#54
0seq_detector.seq_in
b00010 seq_detector.state
b00100 seq_detector.next
#55
1seq_detector.seq_in
b00100 seq_detector.state
b01000 seq_detector.next
#56
b01000 seq_detector.state
b10000 seq_detector.next
#57
0seq_detector.seq_in
b10000 seq_detector.state
b00001 seq_detector.next
#58
1seq_detector.detect_out
b00001 seq_detector.state
